pycoupang/__init__.py
pycoupang/base.py
pycoupang/category.py
pycoupang/client.py
pycoupang/logistics.py
pycoupang/product.py
pycoupang/settlement.py
python_coupang-0.1.2.dist-info/LICENSE
python_coupang-0.1.2.dist-info/METADATA
python_coupang-0.1.2.dist-info/WHEEL
python_coupang-0.1.2.dist-info/top_level.txt
python_coupang-0.1.2.dist-info/RECORD
