Metadata-Version: 2.1
Name: python-coupang
Version: 0.1.2
Summary: A Python client for the Coupang API
Author: Chris Han
License: MIT License
Project-URL: Homepage, https://github.com/christopherhan/python-coupang
Keywords: coupang,api,client
Classifier: Development Status :: 3 - Alpha
Classifier: Intended Audience :: Developers
Classifier: License :: OSI Approved :: MIT License
Classifier: Operating System :: OS Independent
Classifier: Programming Language :: Python :: 3
Classifier: Programming Language :: Python :: 3.6
Classifier: Programming Language :: Python :: 3.7
Classifier: Programming Language :: Python :: 3.8
Classifier: Programming Language :: Python :: 3.9
Requires-Python: >=3.6
License-File: LICENSE
Requires-Dist: requests>=2.25.1
Requires-Dist: pytest>=6.2.3
Requires-Dist: python-dotenv>=0.19.0
